functional/ConTextDocument.py
functional/ConTextItem.py
functional/ConTextMarkup.py
functional/__init__.py
functional/itemData.py
functional/process.py
functional/processReports.py
functional/tagItem.py
functional/templates.py
functional/version.py
functional/tests/__init__.py
functional/tests/test_ConTextItem.py
functional/tests/tests1.py
pyConTextNLP/ConTextMarkup.py
pyConTextNLP/__init__.py
pyConTextNLP/helpers.py
pyConTextNLP/itemData.py
pyConTextNLP/itemData_backup.py
pyConTextNLP/pyConText.py
pyConTextNLP/pyConTextGraph.py
pyConTextNLP/tagObject.py
pyConTextNLP/utils.py
pyConTextNLP/version.py
pyConTextNLP/display/__init__.py
pyConTextNLP/display/_bokeh.py
pyConTextNLP/display/_mpld3.py
pyConTextNLP/display/html.py
pyConTextNLP/functional/ConTextDocument.py
pyConTextNLP/functional/ConTextItem.py
pyConTextNLP/functional/ConTextMarkup.py
pyConTextNLP/functional/__init__.py
pyConTextNLP/functional/itemData.py
pyConTextNLP/functional/process.py
pyConTextNLP/functional/processReports.py
pyConTextNLP/functional/tagItem.py
pyConTextNLP/functional/templates.py
pyConTextNLP/functional/tests/__init__.py
pyConTextNLP/functional/tests/test_contextitem.py
pyConTextNLP/functional/tests/test_contextmarkup.py
pyConTextNLP/functional/tests/test_env.py
pyConTextNLP/functional/tests/test_helpers.py
pyConTextNLP/functional/tests/test_itemData.py
pyConTextNLP/io/__init__.py
pyConTextNLP/io/xml.py
pyConTextNLP/tests/__init__.py
pyConTextNLP/tests/helper_tests.py
pyConTextNLP/tests/test_alec.py
pyConTextNLP/tests/test_base.py
pyConTextNLP/tests/test_contextitem.py
pyConTextNLP/tests/test_contextmarkup.py
pyConTextNLP/tests/test_env.py
pyConTextNLP/tests/test_helpers.py
pyConTextNLP/tests/test_itemData.py
pyConTextNLP-0.7.0.1.dist-info/METADATA
pyConTextNLP-0.7.0.1.dist-info/WHEEL
pyConTextNLP-0.7.0.1.dist-info/top_level.txt
pyConTextNLP-0.7.0.1.dist-info/RECORD
