Metadata-Version: 2.1
Name: pyConTextNLP
Version: 0.7.0.1
Summary: A Python implementation of the ConText algorithm
Home-page: https://github.com/chapmanbe/pyConTextNLP
Author: Brian Chapman
Author-email: brian.chapman@utah.edu
License: http://www.apache.org/licenses/LICENSE-2.0
Keywords: ConText NLP
Platform: UNKNOWN
Classifier: Development Status :: 4 - Beta
Classifier: Programming Language :: Python :: 3
Requires-Dist: networkx
Requires-Dist: pyyaml
Provides-Extra: dev
Requires-Dist: check-manifest ; extra == 'dev'
Provides-Extra: test
Requires-Dist: coverage ; extra == 'test'
